orm_filter/__init__.py
orm_filter/filter.py
django_orm_filter-0.1.0.dist-info/LICENSE
django_orm_filter-0.1.0.dist-info/METADATA
django_orm_filter-0.1.0.dist-info/WHEEL
django_orm_filter-0.1.0.dist-info/top_level.txt
django_orm_filter-0.1.0.dist-info/RECORD
