Metadata-Version: 2.1
Name: django-orm-filter
Version: 0.1.0
Summary: django drf query filter
Home-page: https://github.com/januwA/django-orm-filter
Author: Ajanuw
Author-email: ajanuw1995@gmail.com
License: UNKNOWN
Project-URL: Bug Tracker, https://github.com/januwA/django-orm-filter/issues
Platform: UNKNOWN
Classifier: Programming Language :: Python :: 3
Classifier: License :: OSI Approved :: MIT License
Classifier: Operating System :: OS Independent
Requires-Python: >=3.6
License-File: LICENSE
Requires-Dist: django
Requires-Dist: djangorestframework
